scratchback/__init__.py
scratchback/instagram.py
scratchback/naver_news.py
test/__init__.py
test/instagram_test.py
test/test_naver_news.py
scratchback-0.2.dist-info/METADATA
scratchback-0.2.dist-info/WHEEL
scratchback-0.2.dist-info/top_level.txt
scratchback-0.2.dist-info/RECORD
