Metadata-Version: 2.1
Name: scratchback
Version: 0.2
Summary: Crawler for Proggraming Course
Home-page: https://github.com/shaynekang/scratchback
Author: DS School
Author-email: support@dsschool.co.kr
License: UNKNOWN
Platform: UNKNOWN
Classifier: Programming Language :: Python :: 3
Classifier: License :: OSI Approved :: MIT License
Classifier: Operating System :: OS Independent
